pycloud/__init__.py
pycloud/core.py
pycloud_ai/__init__.py
pycloud_ai/core.py
pycloud_ai-0.1.dist-info/LICENSE.txt
pycloud_ai-0.1.dist-info/METADATA
pycloud_ai-0.1.dist-info/WHEEL
pycloud_ai-0.1.dist-info/top_level.txt
pycloud_ai-0.1.dist-info/RECORD
